MANIFEST.in
README.md
setup.cfg
setup.py
bin/possel
possel/__init__.py
possel/irc.py
possel_server.egg-info/PKG-INFO
possel_server.egg-info/SOURCES.txt
possel_server.egg-info/dependency_links.txt
possel_server.egg-info/not-zip-safe
possel_server.egg-info/requires.txt
possel_server.egg-info/top_level.txt