Metadata-Version: 1.1
Name: possel-server
Version: 0.2.2
Summary: Python-based IRC "bouncer", requires custom clients for scrollback.
Home-page: https://bitbucket.org/KitB/possel/
Author: Kit Barnes
Author-email: kit@ninjalith.com
License: BSD
Keywords: irc quassel
Platform: UNKNOWN
Classifier: Development Status :: 2 - Pre-Alpha
Classifier: Topic :: Communications :: Chat :: Internet Relay Chat
Classifier: License :: OSI Approved :: BSD License
Classifier: Programming Language :: Python :: 3 :: Only
